Metadata-Version: 2.1
Name: pipertask
Version: 0.1.0
Summary: The base package to extend to create a Piper Task
Home-page: https://github.com/piper-tools/pipertask
Author: Federico Pugliese
Author-email: federico.pugliese.wr@gmail.com
License: Apache Software License, Version 2.0
Platform: UNKNOWN
Classifier: License :: OSI Approved :: Apache Software License
Classifier: Development Status :: 3 - Alpha
Classifier: Intended Audience :: Developers
Classifier: Programming Language :: Python :: 3
Classifier: Programming Language :: Python :: 3.7
Requires-Python: >=3.7
